Seg2DetAugment/__init__.py
Seg2DetAugment/augment.py
Seg2DetAugment-0.0.4.dist-info/LICENSE
Seg2DetAugment-0.0.4.dist-info/METADATA
Seg2DetAugment-0.0.4.dist-info/WHEEL
Seg2DetAugment-0.0.4.dist-info/top_level.txt
Seg2DetAugment-0.0.4.dist-info/RECORD
