Metadata-Version: 2.1
Name: Seg2DetAugment
Version: 0.0.4
Summary: A data augmentation package for converting segmentation data to detection data.
Home-page: https://github.com/Huuuuugh/Seg2DetAugment
Author: XavierHugh
Author-email: 2396392765@qq.com
Classifier: Programming Language :: Python :: 3
Classifier: License :: OSI Approved :: MIT License
Classifier: Operating System :: OS Independent
Requires-Python: >=3.6
License-File: LICENSE
Requires-Dist: numpy
Requires-Dist: pandas
Requires-Dist: opencv-python
